pytorch_lightning_enterprise/__init__.py
pytorch_lightning_enterprise/__init__.pyc
pytorch_lightning_enterprise/accelerators/__init__.py
pytorch_lightning_enterprise/accelerators/__init__.pyc
pytorch_lightning_enterprise/accelerators/xla.pyc
pytorch_lightning_enterprise/loggers/__init__.py
pytorch_lightning_enterprise/loggers/__init__.pyc
pytorch_lightning_enterprise/loggers/comet.pyc
pytorch_lightning_enterprise/loggers/logger.pyc
pytorch_lightning_enterprise/loggers/mlflow.pyc
pytorch_lightning_enterprise/loggers/neptune.pyc
pytorch_lightning_enterprise/loggers/wandb.pyc
pytorch_lightning_enterprise/plugins/__init__.py
pytorch_lightning_enterprise/plugins/__init__.pyc
pytorch_lightning_enterprise/plugins/environments/__init__.py
pytorch_lightning_enterprise/plugins/environments/__init__.pyc
pytorch_lightning_enterprise/plugins/environments/kubeflow.pyc
pytorch_lightning_enterprise/plugins/environments/lsf.pyc
pytorch_lightning_enterprise/plugins/environments/slurm.pyc
pytorch_lightning_enterprise/plugins/environments/torchelastic.pyc
pytorch_lightning_enterprise/plugins/environments/xla.pyc
pytorch_lightning_enterprise/plugins/io/__init__.py
pytorch_lightning_enterprise/plugins/io/__init__.pyc
pytorch_lightning_enterprise/plugins/io/xla.pyc
pytorch_lightning_enterprise/plugins/precision/__init__.py
pytorch_lightning_enterprise/plugins/precision/__init__.pyc
pytorch_lightning_enterprise/plugins/precision/bitsandbytes.pyc
pytorch_lightning_enterprise/plugins/precision/deepspeed.pyc
pytorch_lightning_enterprise/plugins/precision/fsdp2.pyc
pytorch_lightning_enterprise/plugins/precision/transformer_engine.pyc
pytorch_lightning_enterprise/plugins/precision/utils.pyc
pytorch_lightning_enterprise/plugins/precision/xla.pyc
pytorch_lightning_enterprise/strategies/__init__.py
pytorch_lightning_enterprise/strategies/__init__.pyc
pytorch_lightning_enterprise/strategies/deepspeed.pyc
pytorch_lightning_enterprise/strategies/fsdp2.pyc
pytorch_lightning_enterprise-2.6.0.dist-info/licenses/LICENSE
pytorch_lightning_enterprise-2.6.0.dist-info/METADATA
pytorch_lightning_enterprise-2.6.0.dist-info/WHEEL
pytorch_lightning_enterprise-2.6.0.dist-info/top_level.txt
pytorch_lightning_enterprise-2.6.0.dist-info/RECORD
