Metadata-Version: 2.4
Name: pytorch_lightning_enterprise
Version: 2.6.0
Summary: Enterprise-Grade extensions for PyTorch Lightning
Author-email: Lightning-AI <developer@lightning.ai>
Project-URL: Homepage, https://lightning.ai
Project-URL: Documentation, https://lightning.ai/docs/
Keywords: deep learning,machine learning,pytorch,AI
Classifier: Programming Language :: Python :: 3
Requires-Python: >=3.10
License-File: LICENSE
Requires-Dist: lightning-sdk>=2025.10.23
Requires-Dist: lightning-utilities
Requires-Dist: torch
Requires-Dist: typing-extensions>4.5.0
Provides-Extra: loggers
Requires-Dist: neptune>=1.14.0; extra == "loggers"
Requires-Dist: wandb>=0.12.10; extra == "loggers"
Requires-Dist: comet-ml>=3.1.0; extra == "loggers"
Requires-Dist: mlflow>=1.0.0; extra == "loggers"
Provides-Extra: lowprecision
Requires-Dist: bitsandbytes<0.47.0,>=0.45.2; extra == "lowprecision"
Provides-Extra: strategies
Requires-Dist: deepspeed<0.17.0,>=0.15.0; (platform_system != "Windows" and platform_system != "Darwin") and extra == "strategies"
Dynamic: license-file
